odoo/addons/base_business_document_import/README.rst
odoo/addons/base_business_document_import/__init__.py
odoo/addons/base_business_document_import/__manifest__.py
odoo/addons/base_business_document_import/i18n/cs_CZ.po
odoo/addons/base_business_document_import/i18n/fr.po
odoo/addons/base_business_document_import/models/__init__.py
odoo/addons/base_business_document_import/models/business_document_import.py
odoo/addons/base_business_document_import/tests/__init__.py
odoo/addons/base_business_document_import/tests/test_business_document_import.py
odoo11_addon_base_business_document_import-11.0.1.0.1.dist-info/DESCRIPTION.rst
odoo11_addon_base_business_document_import-11.0.1.0.1.dist-info/METADATA
odoo11_addon_base_business_document_import-11.0.1.0.1.dist-info/RECORD
odoo11_addon_base_business_document_import-11.0.1.0.1.dist-info/WHEEL
odoo11_addon_base_business_document_import-11.0.1.0.1.dist-info/metadata.json
odoo11_addon_base_business_document_import-11.0.1.0.1.dist-info/top_level.txt
