Metadata-Version: 2.0
Name: odoo11-addon-base-business-document-import
Version: 11.0.1.0.1
Summary: Provides technical tools to import sale orders or supplier invoices
Home-page: https://github.com/OCA/edi
Author: Akretion, Nicolas JEUDY, Odoo Community Association (OCA)
Author-email: support@odoo-community.org
License: AGPL-3
Platform: UNKNOWN
Classifier: Programming Language :: Python
Classifier: Framework :: Odoo
Classifier: License :: OSI Approved :: GNU Affero General Public License v3
Requires-Python: >=2.7, !=3.0.*, !=3.1.*, !=3.2.*, !=3.3.*, !=3.4.*
Requires-Dist: PyPDF2
Requires-Dist: odoo (<11.1dev,>=11.0a)
Requires-Dist: odoo11-addon-account-tax-unece
Requires-Dist: odoo11-addon-base-vat-sanitized
Requires-Dist: odoo11-addon-product-uom-unece
